{"config": {"path": {"label": "./Dataset/dataset202312/dataset.csv", "pretrained": null, "position": "./position.csv", "submodel_name": "./submodel_name.csv", "unlearn": "", "record": "./record.csv", "result": "./result.json"}, "folder": {"dataset": "./Dataset/dataset202312/data", "vectorize": "./Vectorize/dataset202312_data", "model": "./Model/dataset202312_data/", "predict": "./Predict/dataset202312_data", "embedding": "./Embedding/", "unlearn": "./Unlearn/", "explain": "./Explain/"}, "model": {"model_name": "VGG16", "batch_size": 4, "train_ratio": 0.8, "learning_rate": 0.0005, "epochs": 3, "shard": 8, "slice": 8, "print_information": "", "hidden_dim": 100, "shard_count": 2, "slice_count": 2}, "classify": false}, "label": [{"_id": "667e748e14ebb5cc007729fe", "removed": false, "chosen": true, "enabled": true, "filename": "22368c1d15d993a8a9d2b83d1ca15beec2e0d80a63ba5792eba024d595e45d12", "label": "benignware", "family": "", "CPUArchitecture": "ARM", "fileSize": "34684", "tags": "test", "isPublic": false, "created": "2024-06-28T08:30:06.582Z", "updated": "2024-06-28T08:30:06.582Z", "__v": 0}, {"_id": "667e748e14ebb5cc007729fd", "removed": false, "chosen": true, "enabled": true, "filename": "22361fb038a48dfe478fee5cac6a8081554afc46df4e9d529277b933a8c8a852", "label": "benignware", "family": "", "CPUArchitecture": "ARM", "fileSize": "88802", "tags": "test", "isPublic": false, "created": "2024-06-28T08:30:06.582Z", "updated": "2024-06-28T08:30:06.582Z", "__v": 0}, {"_id": "667e748e14ebb5cc00772a01", "removed": false, "chosen": true, "enabled": true, "filename": "2258db072ee164c260222f8e6caf01e3168f5086bc9360b6d14d9d31cd9352eb", "label": "benignware", "family": "", "CPUArchitecture": "ARM", "fileSize": "25100", "tags": "test", "isPublic": false, "created": "2024-06-28T08:30:06.582Z", "updated": "2024-06-28T08:30:06.582Z", "__v": 0}, {"_id": "667e748e14ebb5cc007729ff", "removed": false, "chosen": true, "enabled": true, "filename": "22386dd08714330375a210cf0706dea0303668741d32a0314ed56bf7aa4be156", "label": "benignware", "family": "", "CPUArchitecture": "ARM", "fileSize": "71312", "tags": "test", "isPublic": false, "created": "2024-06-28T08:30:06.582Z", "updated": "2024-06-28T08:30:06.582Z", "__v": 0}, {"_id": "667e748e14ebb5cc007729fb", "removed": false, "chosen": true, "enabled": true, "filename": "222d04632af2ced38ac5a41ef03cd8287ca9874e3a01bc38352f7f6d67b12822", "label": "benignware", "family": "", "CPUArchitecture": "ARM", "fileSize": "14112", "tags": "test", "isPublic": false, "created": "2024-06-28T08:30:06.582Z", "updated": "2024-06-28T08:30:06.582Z", "__v": 0}, {"_id": "667e748e14ebb5cc00772a00", "removed": false, "chosen": true, "enabled": true, "filename": "223f8a33d0c082f8e14591affb05a649cdcbb14a03b4fbfccff6f8a1b73fe6ae", "label": "benignware", "family": "", "CPUArchitecture": "ARM", "fileSize": "190872", "tags": "test", "isPublic": false, "created": "2024-06-28T08:30:06.582Z", "updated": "2024-06-28T08:30:06.582Z", "__v": 0}, {"_id": "667e748e14ebb5cc00772a02", "removed": false, "chosen": true, "enabled": true, "filename": "2260bc05459600385953efd819f86b755fd1dd68cfbdcd8930e08130a0d3a912", "label": "benignware", "family": "", "CPUArchitecture": "ARM", "fileSize": "99776", "tags": "test", "isPublic": false, "created": "2024-06-28T08:30:06.582Z", "updated": "2024-06-28T08:30:06.582Z", "__v": 0}, {"_id": "667e748e14ebb5cc007729fc", "removed": false, "chosen": true, "enabled": true, "filename": "22342984acac8290f231c6b17f31f0ee2a5be84d058e4a6913a1c8c6cca2b71b", "label": "benignware", "family": "", "CPUArchitecture": "ARM", "fileSize": "20704", "tags": "test", "isPublic": false, "created": "2024-06-28T08:30:06.582Z", "updated": "2024-06-28T08:30:06.582Z", "__v": 0}, {"_id": "667e748e14ebb5cc007729fa", "removed": false, "chosen": true, "enabled": true, "filename": "222833f73ce0b5ac8b60f2d6a46100b0925f271843ffe6db137094f5f542e4f0", "label": "benignware", "family": "", "CPUArchitecture": "ARM", "fileSize": "21868", "tags": "test", "isPublic": false, "created": "2024-06-28T08:30:06.582Z", "updated": "2024-06-28T08:30:06.582Z", "__v": 0}, {"_id": "667e748e14ebb5cc007729f0", "removed": false, "chosen": true, "enabled": true, "filename": "21e6ed98b71955e8dca5bc7dd698d6ea5a9c3a918a512fdc7e4f00a8848af662", "label": "benignware", "family": "", "CPUArchitecture": "ARM", "fileSize": "92368", "tags": "test", "isPublic": false, "created": "2024-06-28T08:30:06.581Z", "updated": "2024-06-28T08:30:06.581Z", "__v": 0}]}